LICENSE
bigearthnet_encoder/__init__.py
bigearthnet_encoder/_tif_reader.py
bigearthnet_encoder/encoder.py
bigearthnet_encoder/metadata_utils.py
bigearthnet_encoder-0.3.0.dist-info/entry_points.txt
bigearthnet_encoder-0.3.0.dist-info/WHEEL
bigearthnet_encoder-0.3.0.dist-info/METADATA
bigearthnet_encoder-0.3.0.dist-info/license_files/LICENSE
bigearthnet_encoder-0.3.0.dist-info/RECORD
