Metadata-Version: 2.1
Name: bigearthnet-encoder
Version: 0.3.0
Summary: A flexible BigEarthNet encoder that allows one to quickly convert BigEarthNet to a DL-optimization data format.
License: Apache Software License 2.0
Author-email: Kai Norman Clasen <k.clasen@protonmail.com>
Requires-Python: >=3.8
Requires-Dist: bigearthnet-common>=2.8
Requires-Dist: bigearthnet-patch-interface>=0.1
Requires-Dist: fastcore>=1.3
Requires-Dist: lmdb>=1.3.0
Requires-Dist: numpy>=1.19
Requires-Dist: pandas>=1.3
Requires-Dist: pydantic>=1.8
Requires-Dist: rasterio>=1.2
Requires-Dist: typer[all]>=0.6
Project-URL: documentation, https://kai-tub.github.io/bigearthnet_encoder
Project-URL: homepage, https://github.com/kai-tub/bigearthnet_encoder/
Project-URL: repository, https://github.com/kai-tub/bigearthnet_encoder/
